{
  "verse": "അവൾ അവന്റെ വസ്ത്രം പിടിച്ചു: എന്നോടു കൂടെ ശയിക്ക എന്നു പറഞ്ഞു: എന്നാൽ അവൻ തന്റെ വസ്ത്രം അവളുടെ കയ്യിൽ വിട്ടേച്ചു പുറത്തേക്കു ഓടിക്കളഞ്ഞു.",
  "book": "1",
  "chapterCount": "50",
  "chapter": "39",
  "verseCountInBook": "1533",
  "verseCountInChapter": "23",
  "verseNumber": "12",
  "bookNameMalayalam": "ഉല്‍‍പത്തി",
  "bookNameEnglish": "Genesis",
  "writerMalayalam": "മോശെ",
  "writerEnglish": "Moses",
  "dateInEnglish": "B.C. 1450-1410 (assumption)",
  "dateInMalayalam": "ബി.സി. 1450-1410 (അനുമാനം)",
  "categoryInEnglish": "Law",
  "categoryInMalayalam": "നിയമം"
}