{
  "verse": "പിന്നെ യഹോവ മോശെയോടു: നീ എന്റെ അടുക്കൽ പർവ്വതത്തിൽ കയറിവന്നു അവിടെ ഇരിക്ക; ഞാൻ നിനക്കു കല്പലകകളും നീ അവരെ ഉപദേശിക്കേണ്ടതിന്നു ഞാൻ എഴുതിയ ന്യായപ്രമാണവും കല്പനകളും തരും എന്നു അരുളിച്ചെയ്തു.",
  "book": "2",
  "chapterCount": "40",
  "chapter": "24",
  "verseCountInBook": "1213",
  "verseCountInChapter": "18",
  "verseNumber": "12",
  "bookNameMalayalam": "പുറപ്പാട്",
  "bookNameEnglish": "Exodus",
  "writerMalayalam": "മോശെ",
  "writerEnglish": "Moses",
  "dateInEnglish": "B.C. 1450-1405 (assumption)",
  "dateInMalayalam": "ബി.സി. 1450-1405 (അനുമാനം)",
  "categoryInEnglish": "Law",
  "categoryInMalayalam": "നിയമം"
}