{
  "verse": "ഞങ്ങളുടെ വെള്ളം ഞങ്ങൾ വിലെക്കു വാങ്ങി കുടിക്കുന്നു; ഞങ്ങളുടെ വിറകു ഞങ്ങൾ വിലകൊടുത്തു മേടിക്കുന്നു.",
  "book": "25",
  "chapterCount": "5",
  "chapter": "5",
  "verseCountInBook": "154",
  "verseCountInChapter": "22",
  "verseNumber": "4",
  "bookNameMalayalam": "വിലാപങ്ങൾ",
  "bookNameEnglish": "Lamentations",
  "writerMalayalam": "യിരെമ്യാവ്",
  "writerEnglish": "Jeremiah",
  "dateInEnglish": "B.C. 556",
  "dateInMalayalam": "ബി.സി. 556",
  "categoryInEnglish": "Prophecy",
  "categoryInMalayalam": "പ്രവചനം"
}