{
  "verse": "യഹോവ ദേശമൊക്കെയും നമ്മുടെ കയ്യിൽ ഏല്പിച്ചിരിക്കുന്നു നിശ്ചയം; ദേശത്തിലെ നിവാസികൾ എല്ലാവരും നമ്മുടെ നിമിത്തം ഉരുകിപ്പോകുന്നു എന്നു അവർ യോശുവയോടു പറഞ്ഞു.",
  "book": "6",
  "chapterCount": "24",
  "chapter": "2",
  "verseCountInBook": "658",
  "verseCountInChapter": "24",
  "verseNumber": "24",
  "bookNameMalayalam": "യോശുവ",
  "bookNameEnglish": "Joshua",
  "writerMalayalam": "യോശുവ",
  "writerEnglish": "Joshua",
  "dateInEnglish": "Not clear",
  "dateInMalayalam": "വ്യക്തമല്ല",
  "categoryInEnglish": "History",
  "categoryInMalayalam": "ചരിത്രം"
}