{
  "verse": "തന്റെ മഹത്വത്താലും വീര്യത്താലും നമ്മെ വിളിച്ചവന്റെ പരിജ്ഞാനത്താൽ അവന്റെ ദിവ്യശക്തി ജീവന്നും ഭക്തിക്കും വേണ്ടിയതു ഒക്കെയും നമുക്കു ദാനം ചെയ്തിരിക്കുന്നുവല്ലോ.",
  "book": "61",
  "chapterCount": "3",
  "chapter": "1",
  "verseCountInBook": "61",
  "verseCountInChapter": "21",
  "verseNumber": "3",
  "bookNameMalayalam": "2 പത്രൊസ്",
  "bookNameEnglish": "2 Peter",
  "writerMalayalam": "പത്രൊസ്",
  "writerEnglish": "Peter",
  "dateInEnglish": "A.D. 64",
  "dateInMalayalam": "ഏ.ഡി. 64",
  "categoryInEnglish": "Epistle",
  "categoryInMalayalam": "ലേഖനം"
}