{
  "verse": "അതുകൊണ്ടു മതിലില്ലാത്ത പട്ടണങ്ങളിൽ പാർക്കുന്ന നാട്ടുപുറങ്ങളിലെ യെഹൂദന്മാർ ആദാർമാസം പതിന്നാലാം തിയ്യതിയെ സന്തോഷവും വിരുന്നും ഉള്ള ദിവസവും ഉത്സവദിനവും ആയിട്ടു ആചരിക്കയും തമ്മിൽ തമ്മിൽ സമ്മാനങ്ങൾ കൊടുത്തയക്കുകയും ചെയ്യുന്നു.",
  "book": "17",
  "chapterCount": "10",
  "chapter": "9",
  "verseCountInBook": "167",
  "verseCountInChapter": "32",
  "verseNumber": "19",
  "bookNameMalayalam": "എസ്ഥേർ",
  "bookNameEnglish": "Esther",
  "writerMalayalam": "മൊർദെഖായി (അനുമാനം)",
  "writerEnglish": " Mordechai (assumption)",
  "dateInEnglish": "B.C. 483-471",
  "dateInMalayalam": "ബി.സി. 483-471",
  "categoryInEnglish": "History",
  "categoryInMalayalam": "ചരിത്രം"
}