{
  "verse": "അതു കേട്ടിട്ടു മഹാപുരോഹിതന്മാരും ശാസ്ത്രിമാരും അവനെ നശിപ്പിക്കേണ്ടതു എങ്ങനെ എന്നു അന്വേഷിച്ചു. പുരുഷാരം എല്ലാം അവന്റെ ഉപദേശത്തിൽ അതിശയിക്കയാൽ അവർ അവനെ ഭയപ്പെട്ടിരുന്നു.",
  "book": "41",
  "chapterCount": "16",
  "chapter": "11",
  "verseCountInBook": "678",
  "verseCountInChapter": "33",
  "verseNumber": "18",
  "bookNameMalayalam": "മർക്കൊസ്",
  "bookNameEnglish": "Mark",
  "writerMalayalam": "മർക്കൊസ്",
  "writerEnglish": "Mark",
  "dateInEnglish": "A.D. 57-63",
  "dateInMalayalam": "ഏ.ഡി. 57-63",
  "categoryInEnglish": "Gospel",
  "categoryInMalayalam": "സുവിശേഷം"
}