{
  "verse": "പിന്നെ നിന്റെ ദൈവമായ യഹോവയുടെ സന്നിധിയിൽ നീ പ്രസ്താവിക്കേണ്ടതു എന്തെന്നാൽ: എന്റെ പിതാവു ദേശാന്തരിയായോരു അരാമ്യനായിരുന്നു; ചുരുക്കംപേരോടു കൂടി അവൻ മിസ്രയീമിലേക്കു ഇറങ്ങിച്ചെന്നു പരദേശിയായി പാർത്തു; അവിടെ വലിപ്പവും ബലവും പെരുപ്പവുമുള്ള ജനമായിത്തീർന്നു.",
  "book": "5",
  "chapterCount": "34",
  "chapter": "26",
  "verseCountInBook": "959",
  "verseCountInChapter": "19",
  "verseNumber": "5",
  "bookNameMalayalam": "ആവർത്തനപുസ്തകം",
  "bookNameEnglish": "Deuteronomy",
  "writerMalayalam": "മോശെ",
  "writerEnglish": "Moses",
  "dateInEnglish": "B.C. 1407-1406 (assumption)",
  "dateInMalayalam": "ബി.സി. 1407-1406 (അനുമാനം)",
  "categoryInEnglish": "Law",
  "categoryInMalayalam": "നിയമം"
}