{
  "verse": "നമ്മുടെ കർത്താവായ യേശുക്രിസ്തു സമ്പന്നൻ ആയിരുന്നിട്ടും അവന്റെ ദാരിദ്ര്യത്താൽ നിങ്ങൾ സമ്പന്നർ ആകേണ്ടതിന്നു നിങ്ങൾ നിമിത്തം ദരിദ്രനായിത്തീർന്ന കൃപ നിങ്ങൾ അറിയുന്നുവല്ലോ.",
  "book": "47",
  "chapterCount": "13",
  "chapter": "8",
  "verseCountInBook": "257",
  "verseCountInChapter": "24",
  "verseNumber": "9",
  "bookNameMalayalam": "2 കൊരിന്ത്യർ",
  "bookNameEnglish": "2 Corinthians",
  "writerMalayalam": "പൌലൊസ്",
  "writerEnglish": "Paul",
  "dateInEnglish": "A.D. 55-57",
  "dateInMalayalam": "ഏ.ഡി. 55-57",
  "categoryInEnglish": "Epistle",
  "categoryInMalayalam": "ലേഖനം"
}