{
  "verse": "ഫെലിസ്ത്യർ ഇപ്പുറത്തു ഒരു മലഞ്ചരിവിലും യിസ്രായേല്യർ അപ്പുറത്തു ഒരു മലഞ്ചരിവിലും നിന്നു; അവരുടെ മദ്ധ്യേ ഒരു താഴ്വര ഉണ്ടായിരുന്നു.",
  "book": "9",
  "chapterCount": "31",
  "chapter": "17",
  "verseCountInBook": "810",
  "verseCountInChapter": "58",
  "verseNumber": "3",
  "bookNameMalayalam": "1 ശമൂവേൽ",
  "bookNameEnglish": "1 Samuel",
  "writerMalayalam": "ശമുവേൽ (നാഥാൻ, ഗാദ്)",
  "writerEnglish": "Samuel (Nathan, Gad)",
  "dateInEnglish": "Not clear",
  "dateInMalayalam": "വ്യക്തമല്ല",
  "categoryInEnglish": "History",
  "categoryInMalayalam": "ചരിത്രം"
}