{
  "verse": "ഇവ വർജ്ജിച്ചു സൂക്ഷിച്ചുകൊണ്ടാൽ നന്നു; ശുഭമായിരിപ്പിൻ.",
  "book": "44",
  "chapterCount": "28",
  "chapter": "15",
  "verseCountInBook": "1007",
  "verseCountInChapter": "41",
  "verseNumber": "29",
  "bookNameMalayalam": "അപ്പൊസ്തലന്മാരുടെ പ്രവൃത്തികൾ",
  "bookNameEnglish": "Acts of the Apostles",
  "writerMalayalam": "വൈദ്യനായ ലൂക്കോസ്",
  "writerEnglish": "Luke the physician",
  "dateInEnglish": "A.D. 63",
  "dateInMalayalam": "ഏ.ഡി. 63",
  "categoryInEnglish": "History",
  "categoryInMalayalam": "ചരിത്രം"
}