{
  "verse": "ഹെരോദാവിന്റെ അടുക്കൽ മടങ്ങിപ്പോകരുതു എന്നു സ്വപ്നത്തിൽ അരുളപ്പാടുണ്ടായിട്ടു അവർ വേറെ വഴിയായി സ്വദേശത്തേക്കു മടങ്ങിപ്പോയി.",
  "book": "40",
  "chapterCount": "28",
  "chapter": "2",
  "verseCountInBook": "1071",
  "verseCountInChapter": "23",
  "verseNumber": "12",
  "bookNameMalayalam": "മത്തായി",
  "bookNameEnglish": "Matthew",
  "writerMalayalam": "മത്തായി",
  "writerEnglish": "Matthew",
  "dateInEnglish": "A.D. 37 (assumption)",
  "dateInMalayalam": "ഏ.ഡി. 37",
  "categoryInEnglish": "Gospel",
  "categoryInMalayalam": "സുവിശേഷം"
}