{
  "verse": "അന്നത്തേക്കു ഒരുങ്ങിയിരിക്കേണമെന്നു സകലജാതികൾക്കും പരസ്യം ചെയ്യേണ്ടതിന്നു കൊടുത്ത തീർപ്പിന്റെ പകർപ്പു ഓരോ സംസ്ഥാനത്തിലും പ്രസിദ്ധമാക്കി.",
  "book": "17",
  "chapterCount": "10",
  "chapter": "3",
  "verseCountInBook": "167",
  "verseCountInChapter": "15",
  "verseNumber": "14",
  "bookNameMalayalam": "എസ്ഥേർ",
  "bookNameEnglish": "Esther",
  "writerMalayalam": "മൊർദെഖായി (അനുമാനം)",
  "writerEnglish": " Mordechai (assumption)",
  "dateInEnglish": "B.C. 483-471",
  "dateInMalayalam": "ബി.സി. 483-471",
  "categoryInEnglish": "History",
  "categoryInMalayalam": "ചരിത്രം"
}