{
  "verse": "ബലമുള്ള ശത്രുവിന്റെ കയ്യിൽനിന്നും എന്നെ പകെച്ചവരുടെ പക്കൽനിന്നും അവൻ എന്നെ വിടുവിച്ചു; അവർ എന്നിലും ബലമേറിയവരായിരുന്നു.",
  "book": "19",
  "chapterCount": "150",
  "chapter": "18",
  "verseCountInBook": "2461",
  "verseCountInChapter": "50",
  "verseNumber": "17",
  "bookNameMalayalam": "സങ്കീർത്തനങ്ങൾ",
  "bookNameEnglish": "Psalms",
  "writerMalayalam": "ദാവീദ്, ആസാഫ്, കോരഹ്‌പുത്രൻമാർ, ശലോമോൻ,  ഹേമാൻ, ഏഥാൻ, മോശെ",
  "writerEnglish": "David, Asaph, Sons of Korah, Solomon, Heman, Ethan, Moses",
  "dateInEnglish": "B.C. 1440-586",
  "dateInMalayalam": "ബി.സി. 1440-586",
  "categoryInEnglish": "Poetry",
  "categoryInMalayalam": "കാവ്യം"
}