{
  "verse": "ഒരുവൻ അദ്ധ്യക്ഷസ്ഥാനം കാംക്ഷിക്കുന്നു എങ്കിൽ നല്ലവേല ആഗ്രഹിക്കുന്നു എന്നുള്ളതു വിശ്വാസയോഗ്യം ആകുന്നു.",
  "book": "54",
  "chapterCount": "6",
  "chapter": "3",
  "verseCountInBook": "113",
  "verseCountInChapter": "16",
  "verseNumber": "1",
  "bookNameMalayalam": "1 തിമൊഥെയൊസ്",
  "bookNameEnglish": "1 Timothy",
  "writerMalayalam": "പൌലൊസ്",
  "writerEnglish": "Paul",
  "dateInEnglish": "A.D. 64",
  "dateInMalayalam": "ഏ.ഡി. 64",
  "categoryInEnglish": "Epistle",
  "categoryInMalayalam": "ലേഖനം"
}