{
  "verse": "“നിന്റെ നിമിത്തം ഞങ്ങളെ ഇടവിടാതെ കൊല്ലുന്നു; അറുപ്പാനുള്ള ആടുകളെപ്പോലെ ഞങ്ങളെ എണ്ണുന്നു” എന്നു എഴുതിയിരിക്കുന്നുവല്ലോ.",
  "book": "45",
  "chapterCount": "16",
  "chapter": "8",
  "verseCountInBook": "433",
  "verseCountInChapter": "39",
  "verseNumber": "36",
  "bookNameMalayalam": "റോമർ",
  "bookNameEnglish": "Romans",
  "writerMalayalam": "പൌലൊസ്",
  "writerEnglish": "Paul",
  "dateInEnglish": "A.D. 57",
  "dateInMalayalam": "ഏ.ഡി. 57",
  "categoryInEnglish": "Epistle",
  "categoryInMalayalam": "ലേഖനം"
}