{
  "verse": "കോരഹ് അവർക്കു വിരോധമായി സർവ്വസഭയെയും സമാഗമനകൂടാരത്തിന്റെ വാതിൽക്കൽ കൂട്ടിവരുത്തി; അപ്പോൾ യഹോവയുടെ തേജസ്സു സർവ്വസഭെക്കും പ്രത്യക്ഷമായി.",
  "book": "4",
  "chapterCount": "36",
  "chapter": "16",
  "verseCountInBook": "1288",
  "verseCountInChapter": "50",
  "verseNumber": "19",
  "bookNameMalayalam": "സംഖ്യാപുസ്തകം",
  "bookNameEnglish": "Numbers",
  "writerMalayalam": "മോശെ",
  "writerEnglish": "Moses",
  "dateInEnglish": "B.C. 1445-1405 (assumption)",
  "dateInMalayalam": "ബി.സി. 1445-1405 (അനുമാനം)",
  "categoryInEnglish": "Law",
  "categoryInMalayalam": "നിയമം"
}