{
  "verse": "മരിച്ചവരിൽ നിന്നു ഉയിർത്തെഴുന്നേൽക്കുമ്പോൾ വിവാഹം കഴിക്കയില്ല വിവാഹത്തിന്നു കൊടുക്കപ്പെടുകയുമില്ല; സ്വർഗ്ഗത്തിലെ ദൂതന്മാരെപ്പോലെ ആകും.",
  "book": "41",
  "chapterCount": "16",
  "chapter": "12",
  "verseCountInBook": "678",
  "verseCountInChapter": "44",
  "verseNumber": "25",
  "bookNameMalayalam": "മർക്കൊസ്",
  "bookNameEnglish": "Mark",
  "writerMalayalam": "മർക്കൊസ്",
  "writerEnglish": "Mark",
  "dateInEnglish": "A.D. 57-63",
  "dateInMalayalam": "ഏ.ഡി. 57-63",
  "categoryInEnglish": "Gospel",
  "categoryInMalayalam": "സുവിശേഷം"
}