{
  "verse": "പ്രായം സംസാരിക്കയും വയോധിക്യം ജ്ഞാനം ഉപദേശിക്കയും ചെയ്യട്ടെ എന്നിങ്ങനെ ഞാൻ വിചാരിച്ചു.",
  "book": "18",
  "chapterCount": "42",
  "chapter": "32",
  "verseCountInBook": "1070",
  "verseCountInChapter": "22",
  "verseNumber": "7",
  "bookNameMalayalam": "ഇയ്യോബ്",
  "bookNameEnglish": "Job",
  "writerMalayalam": "ഇയ്യോബ്",
  "writerEnglish": "Job",
  "dateInEnglish": "B.C. 2000-1800",
  "dateInMalayalam": "ബി.സി. 2000-1800",
  "categoryInEnglish": "Poetry",
  "categoryInMalayalam": "കാവ്യം"
}