{
  "verse": "യിസ്രായേൽമക്കളോടു നീ പറയേണ്ടതു എന്തെന്നാൽ: ഇതു നിങ്ങളുടെ തലമുറകളിൽ എനിക്കു വിശുദ്ധമായ അഭിഷേകതൈലം ആയിരിക്കേണം.",
  "book": "2",
  "chapterCount": "40",
  "chapter": "30",
  "verseCountInBook": "1213",
  "verseCountInChapter": "38",
  "verseNumber": "31",
  "bookNameMalayalam": "പുറപ്പാട്",
  "bookNameEnglish": "Exodus",
  "writerMalayalam": "മോശെ",
  "writerEnglish": "Moses",
  "dateInEnglish": "B.C. 1450-1405 (assumption)",
  "dateInMalayalam": "ബി.സി. 1450-1405 (അനുമാനം)",
  "categoryInEnglish": "Law",
  "categoryInMalayalam": "നിയമം"
}