{
  "verse": "ശൌലിന്റെ മകനായ ഈശ്-ബോശെത്ത് യിസ്രായേലിൽ രാജാവായപ്പോൾ അവന്നു നാല്പതു വയസ്സായിരുന്നു; അവൻ രണ്ടു സംവത്സരം വാണു. യെഹൂദാഗൃഹമോ ദാവീദിനോടു ചേർന്നുനിന്നു. ",
  "book": "10",
  "chapterCount": "24",
  "chapter": "2",
  "verseCountInBook": "695",
  "verseCountInChapter": "32",
  "verseNumber": "10",
  "bookNameMalayalam": "2 ശമൂവേൽ",
  "bookNameEnglish": "2 Samuel",
  "writerMalayalam": "ശമുവേൽ (നാഥാൻ, ഗാദ്)",
  "writerEnglish": "Samuel (Nathan, Gad)",
  "dateInEnglish": "Not clear",
  "dateInMalayalam": "വ്യക്തമല്ല",
  "categoryInEnglish": "History",
  "categoryInMalayalam": "ചരിത്രം"
}