{
  "verse": "എന്നാൽ ഒമ്രിയുടെ പക്ഷം ചേർന്ന ജനം ഗീനത്തിന്റെ മകനായ തിബ്നിയുടെ പക്ഷം ചേർന്ന ജനത്തെ തോല്പിച്ചു; അങ്ങനെ തിബ്നി പട്ടുപോകയും ഒമ്രി രാജാവാകയും ചെയ്തു.",
  "book": "11",
  "chapterCount": "22",
  "chapter": "16",
  "verseCountInBook": "816",
  "verseCountInChapter": "34",
  "verseNumber": "22",
  "bookNameMalayalam": "1 രാജാക്കന്മാർ",
  "bookNameEnglish": "1 Kings",
  "writerMalayalam": "യിരെമ്യാവ്‌",
  "writerEnglish": "Jeremiah",
  "dateInEnglish": "B.C. 630-600",
  "dateInMalayalam": "ബി.സി. 630-600",
  "categoryInEnglish": "History",
  "categoryInMalayalam": "ചരിത്രം"
}