{
  "verse": "മനുഷ്യപുത്രാ, മത്സരഗൃഹമായ യിസ്രായേൽഗൃഹം നിന്നോടു: നീ എന്തു ചെയ്യുന്നു എന്നു ചോദിച്ചില്ലയോ?",
  "book": "26",
  "chapterCount": "48",
  "chapter": "12",
  "verseCountInBook": "1273",
  "verseCountInChapter": "28",
  "verseNumber": "9",
  "bookNameMalayalam": "യെഹെസ്കേൽ",
  "bookNameEnglish": "Ezekiel",
  "writerMalayalam": "യെഹെസ്കേൽ",
  "writerEnglish": "Ezekiel",
  "dateInEnglish": "B.C. 571 (assumption)",
  "dateInMalayalam": "ബി.സി. 571 (അനുമാനം)",
  "categoryInEnglish": "Prophecy",
  "categoryInMalayalam": "പ്രവചനം"
}