{
  "verse": "നിന്റെ പുത്രന്മാരും പുത്രിമാരും അന്യജാതിക്കു അടിമകളാകും; നിന്റെ കണ്ണു ഇടവിടാതെ അവരെ നോക്കിയിരുന്നു ക്ഷീണിക്കും; എങ്കിലും നിന്നാൽ ഒന്നും സാധിക്കയില്ല.",
  "book": "5",
  "chapterCount": "34",
  "chapter": "28",
  "verseCountInBook": "959",
  "verseCountInChapter": "68",
  "verseNumber": "32",
  "bookNameMalayalam": "ആവർത്തനപുസ്തകം",
  "bookNameEnglish": "Deuteronomy",
  "writerMalayalam": "മോശെ",
  "writerEnglish": "Moses",
  "dateInEnglish": "B.C. 1407-1406 (assumption)",
  "dateInMalayalam": "ബി.സി. 1407-1406 (അനുമാനം)",
  "categoryInEnglish": "Law",
  "categoryInMalayalam": "നിയമം"
}