{
  "verse": "ഇന്നു തന്നെ രാജ്ഞിയുടെ പ്രവൃത്തി കേട്ട പാർസ്യയിലെയും മേദ്യയിലെയും പ്രഭുപത്നിമാർ രാജാവിന്റെ സകലപ്രഭുക്കന്മാരോടും അങ്ങനെ തന്നേ പറയും; ഇങ്ങനെ നിന്ദയും നീരസവും അധികരിക്കും.",
  "book": "17",
  "chapterCount": "10",
  "chapter": "1",
  "verseCountInBook": "167",
  "verseCountInChapter": "22",
  "verseNumber": "18",
  "bookNameMalayalam": "എസ്ഥേർ",
  "bookNameEnglish": "Esther",
  "writerMalayalam": "മൊർദെഖായി (അനുമാനം)",
  "writerEnglish": " Mordechai (assumption)",
  "dateInEnglish": "B.C. 483-471",
  "dateInMalayalam": "ബി.സി. 483-471",
  "categoryInEnglish": "History",
  "categoryInMalayalam": "ചരിത്രം"
}