{
  "verse": "മനുഷ്യ പുത്രൻ തന്റെ പിതാവിന്റെ മഹത്വത്തിൽ തന്റെ ദൂതന്മാരുമായി വരും; അപ്പോൾ അവൻ ഓരോരുത്തന്നും അവനവന്റെ പ്രവൃത്തിക്കു തക്കവണ്ണം പകരം നല്കും.",
  "book": "40",
  "chapterCount": "28",
  "chapter": "16",
  "verseCountInBook": "1071",
  "verseCountInChapter": "28",
  "verseNumber": "27",
  "bookNameMalayalam": "മത്തായി",
  "bookNameEnglish": "Matthew",
  "writerMalayalam": "മത്തായി",
  "writerEnglish": "Matthew",
  "dateInEnglish": "A.D. 37 (assumption)",
  "dateInMalayalam": "ഏ.ഡി. 37",
  "categoryInEnglish": "Gospel",
  "categoryInMalayalam": "സുവിശേഷം"
}