{
  "verse": "യാഗത്തിലല്ല കരുണയിൽ അത്രേ ഞാൻ പ്രസാദിക്കുന്നു എന്നുള്ളതു എന്തു എന്നു പോയി പഠിപ്പിൻ. ഞാൻ നീതിമാന്മാരെ അല്ല പാപികളെ അത്രേ വിളിപ്പാൻ വന്നതു” എന്നു പറഞ്ഞു.",
  "book": "40",
  "chapterCount": "28",
  "chapter": "9",
  "verseCountInBook": "1071",
  "verseCountInChapter": "38",
  "verseNumber": "13",
  "bookNameMalayalam": "മത്തായി",
  "bookNameEnglish": "Matthew",
  "writerMalayalam": "മത്തായി",
  "writerEnglish": "Matthew",
  "dateInEnglish": "A.D. 37 (assumption)",
  "dateInMalayalam": "ഏ.ഡി. 37",
  "categoryInEnglish": "Gospel",
  "categoryInMalayalam": "സുവിശേഷം"
}