{
  "verse": "അവൻ പുരുഷാരത്തെ ഇടയനില്ലാത്ത ആടുകളെപ്പോലെ കുഴഞ്ഞവരും ചിന്നിയവരുമായി കണ്ടിട്ടു അവരെക്കുറിച്ചു മനസ്സലിഞ്ഞു, തന്റെ ശിഷ്യന്മാരോടു:",
  "book": "40",
  "chapterCount": "28",
  "chapter": "9",
  "verseCountInBook": "1071",
  "verseCountInChapter": "38",
  "verseNumber": "36",
  "bookNameMalayalam": "മത്തായി",
  "bookNameEnglish": "Matthew",
  "writerMalayalam": "മത്തായി",
  "writerEnglish": "Matthew",
  "dateInEnglish": "A.D. 37 (assumption)",
  "dateInMalayalam": "ഏ.ഡി. 37",
  "categoryInEnglish": "Gospel",
  "categoryInMalayalam": "സുവിശേഷം"
}