{
  "verse": "യഹോവയുടെ മഹാദിവസം അടുത്തിരിക്കുന്നു; അതു അടുത്തു അത്യന്തം ബദ്ധപ്പെട്ടുവരുന്നു; കേട്ടോ യഹോവയുടെ ദിവസം! വീരൻ അവിടെ കഠിനമായി നിലവിളിക്കുന്നു.",
  "book": "36",
  "chapter": "1",
  "verseNumber": "14",
  "bookNameMalayalam": "സെഫന്യാവ്",
  "bookNameEnglish": "Zephaniah",
  "writerMalayalam": "സെഫന്യാവ്",
  "writerEnglish": "Zephaniah",
  "dateInEnglish": "B.C. 640-621",
  "dateInMalayalam": "ബി.സി. 640-621",
  "categoryInEnglish": "Prophecy",
  "categoryInMalayalam": "പ്രവചനം",
  "bookSummary": "യഹോവയുടെ ദിനം, യെഹൂദാ ജനം അവരുടെ പാപങ്ങളെക്കുറിച്ച് അനുതപിക്കുന്നില്ലെങ്കിൽ അവരുടെ മേൽ വരുന്ന ശിക്ഷ, അന്ത്യനാളുകളിൽ ദൈവം അവരുടെ മേൽ അനുഗ്രഹങ്ങൾ വർഷിക്കുമെന്നുള്ള വാഗ്ദത്തം."
}