{
  "verse": "മേൽപുരകളിൽ ആകാശത്തിലെ സൈന്യത്തെ നമസ്കരിക്കുന്നവരെയും യഹോവയെച്ചൊല്ലിയും മൽക്കാമിനെച്ചൊല്ലിയും സത്യം ചെയ്തു നമസ്കരിക്കുന്നവരെയും യഹോവയെ വിട്ടു പിന്മാറിയവരെയും",
  "book": "36",
  "chapterCount": "3",
  "chapter": "1",
  "verseCountInBook": "53",
  "verseCountInChapter": "18",
  "verseNumber": "5",
  "bookNameMalayalam": "സെഫന്യാവ്",
  "bookNameEnglish": "Zephaniah",
  "writerMalayalam": "സെഫന്യാവ്",
  "writerEnglish": "Zephaniah",
  "dateInEnglish": "B.C. 640-621",
  "dateInMalayalam": "ബി.സി. 640-621",
  "categoryInEnglish": "Prophecy",
  "categoryInMalayalam": "പ്രവചനം"
}