{
  "verse": "അവൻ അവർക്കു അരോവേർമുതൽ മിന്നീത്ത്‌വരെയും ആബേൽ-കെരാമീംവരെയും ഒരു മഹാസംഹാരം വരുത്തി, ഇരുപതു പട്ടണം ജയിച്ചടക്കി.",
  "book": "7",
  "chapterCount": "21",
  "chapter": "11",
  "verseCountInBook": "618",
  "verseCountInChapter": "40",
  "verseNumber": "33",
  "bookNameMalayalam": "ന്യായാധിപന്മാർ",
  "bookNameEnglish": "Judges",
  "writerMalayalam": "ശമുവേൽ",
  "writerEnglish": "Samuel",
  "dateInEnglish": "B.C. 1050 (assumption)",
  "dateInMalayalam": "ബി.സി. 1050 (അനുമാനം)",
  "categoryInEnglish": "History",
  "categoryInMalayalam": "ചരിത്രം"
}