{
  "verse": "പിന്നെ നീ അവനെ കാണുന്നില്ല എന്നു പറഞ്ഞാൽ എങ്ങനെ? വ്യവഹാരം അവന്റെ മുമ്പിൽ ഇരിക്കയാൽ നീ അവന്നായി കാത്തിരിക്ക.",
  "book": "18",
  "chapterCount": "42",
  "chapter": "35",
  "verseCountInBook": "1070",
  "verseCountInChapter": "16",
  "verseNumber": "14",
  "bookNameMalayalam": "ഇയ്യോബ്",
  "bookNameEnglish": "Job",
  "writerMalayalam": "ഇയ്യോബ്",
  "writerEnglish": "Job",
  "dateInEnglish": "B.C. 2000-1800",
  "dateInMalayalam": "ബി.സി. 2000-1800",
  "categoryInEnglish": "Poetry",
  "categoryInMalayalam": "കാവ്യം"
}