{
  "verse": "ബഹുജനത്തെ അനുസരിച്ചു ദോഷം ചെയ്യരുതു; ന്യായം മറിച്ചുകളവാൻ ബഹുജനപക്ഷം ചേർന്നു വ്യവഹാരത്തിൽ സാക്ഷ്യം പറയരുതു:",
  "book": "2",
  "chapterCount": "40",
  "chapter": "23",
  "verseCountInBook": "1213",
  "verseCountInChapter": "33",
  "verseNumber": "2",
  "bookNameMalayalam": "പുറപ്പാട്",
  "bookNameEnglish": "Exodus",
  "writerMalayalam": "മോശെ",
  "writerEnglish": "Moses",
  "dateInEnglish": "B.C. 1450-1405 (assumption)",
  "dateInMalayalam": "ബി.സി. 1450-1405 (അനുമാനം)",
  "categoryInEnglish": "Law",
  "categoryInMalayalam": "നിയമം"
}