{
  "verse": "ഈ നഗരം നിശ്ചയമായി ബാബേൽരാജാവിന്റെ സൈന്യത്തിന്റെ കയ്യിൽ ഏല്പിക്കപ്പെടും, അവൻ അതിനെ പിടിക്കും എന്നും",
  "book": "24",
  "chapterCount": "52",
  "chapter": "38",
  "verseCountInBook": "1364",
  "verseCountInChapter": "28",
  "verseNumber": "2",
  "bookNameMalayalam": "യിരെമ്യാവ്",
  "bookNameEnglish": "Jeremiah",
  "writerMalayalam": "യിരെമ്യാവ്",
  "writerEnglish": "Jeremiah",
  "dateInEnglish": "B.C. 627-586",
  "dateInMalayalam": "ബി.സി. 627-586",
  "categoryInEnglish": "Prophecy",
  "categoryInMalayalam": "പ്രവചനം"
}