{
  "verse": "സമാധാനത്തിന്റെ ദൈവമോ വേഗത്തിൽ സാത്താനെ നിങ്ങളുടെ കാൽക്കീഴെ ചതെച്ചുകളയും. നമ്മുടെ കർത്താവായ യേശുക്രിസ്തുവിന്റെ കൃപ നിങ്ങളോടുകൂടെ ഇരിക്കുമാറാകട്ടെ.",
  "book": "45",
  "chapterCount": "16",
  "chapter": "16",
  "verseCountInBook": "433",
  "verseCountInChapter": "27",
  "verseNumber": "20",
  "bookNameMalayalam": "റോമർ",
  "bookNameEnglish": "Romans",
  "writerMalayalam": "പൌലൊസ്",
  "writerEnglish": "Paul",
  "dateInEnglish": "A.D. 57",
  "dateInMalayalam": "ഏ.ഡി. 57",
  "categoryInEnglish": "Epistle",
  "categoryInMalayalam": "ലേഖനം"
}