{
  "verse": "ഇവൻ സുന്ദരം എന്ന ദൈവാലയഗോപുരത്തിങ്കൽ ഭിക്ഷ യാചിച്ചുകൊണ്ടു ഇരുന്നവൻ എന്നു അറിഞ്ഞു അവന്നു സംഭവിച്ചതിനെക്കുറിച്ചു വിസ്മയവും പരിഭ്രമവും നിറഞ്ഞവരായീത്തീർന്നു.",
  "book": "44",
  "chapterCount": "28",
  "chapter": "3",
  "verseCountInBook": "1007",
  "verseCountInChapter": "26",
  "verseNumber": "10",
  "bookNameMalayalam": "അപ്പൊസ്തലന്മാരുടെ പ്രവൃത്തികൾ",
  "bookNameEnglish": "Acts of the Apostles",
  "writerMalayalam": "വൈദ്യനായ ലൂക്കോസ്",
  "writerEnglish": "Luke the physician",
  "dateInEnglish": "A.D. 63",
  "dateInMalayalam": "ഏ.ഡി. 63",
  "categoryInEnglish": "History",
  "categoryInMalayalam": "ചരിത്രം"
}