{
  "verse": "അവൻ എന്നോടു: നോക്കുക മാനുഷകാഷ്ഠത്തിന്നു പകരം ഞാൻ നിനക്കു പശുവിൻ ചാണകം അനുവദിക്കുന്നു; അതു കത്തിച്ചു നിന്റെ അപ്പം ചുട്ടുകൊൾക എന്നു കല്പിച്ചു.",
  "book": "26",
  "chapterCount": "48",
  "chapter": "4",
  "verseCountInBook": "1273",
  "verseCountInChapter": "17",
  "verseNumber": "15",
  "bookNameMalayalam": "യെഹെസ്കേൽ",
  "bookNameEnglish": "Ezekiel",
  "writerMalayalam": "യെഹെസ്കേൽ",
  "writerEnglish": "Ezekiel",
  "dateInEnglish": "B.C. 571 (assumption)",
  "dateInMalayalam": "ബി.സി. 571 (അനുമാനം)",
  "categoryInEnglish": "Prophecy",
  "categoryInMalayalam": "പ്രവചനം"
}