{
  "verse": "കടിഞ്ഞൂലെല്ലാം എനിക്കുള്ളതു; ഞാൻ മിസ്രയീംദേശത്തു കടിഞ്ഞൂലിനെ ഒക്കെയും കൊന്നനാളിൽ യിസ്രായേലിൽ മനുഷ്യന്റെയും മൃഗത്തിന്റെയും കടിഞ്ഞൂലിനെയെല്ലാം എനിക്കായിട്ടു ശുദ്ധീകരിച്ചു; അതു എനിക്കുള്ളതായിരിക്കേണം; ഞാൻ യഹോവ ആകുന്നു.",
  "book": "4",
  "chapterCount": "36",
  "chapter": "3",
  "verseCountInBook": "1288",
  "verseCountInChapter": "51",
  "verseNumber": "13",
  "bookNameMalayalam": "സംഖ്യാപുസ്തകം",
  "bookNameEnglish": "Numbers",
  "writerMalayalam": "മോശെ",
  "writerEnglish": "Moses",
  "dateInEnglish": "B.C. 1445-1405 (assumption)",
  "dateInMalayalam": "ബി.സി. 1445-1405 (അനുമാനം)",
  "categoryInEnglish": "Law",
  "categoryInMalayalam": "നിയമം"
}