{
  "verse": "അബ്രാഹാംപിതാവേ, എന്നോടു കനിവുണ്ടാകേണമേ; ലാസർ വിരലിന്റെ അറ്റം വെള്ളത്തിൽ മുക്കി എന്റെ നാവിനെ തണുപ്പിക്കേണ്ടതിന്നു അവനെ അയക്കേണമേ; ഞാൻ ഈ ജ്വാലയിൽ കിടന്നു വേദന അനുഭവിക്കുന്നു എന്നു വിളിച്ചു പറഞ്ഞു.",
  "book": "42",
  "chapterCount": "24",
  "chapter": "16",
  "verseCountInBook": "1151",
  "verseCountInChapter": "31",
  "verseNumber": "24",
  "bookNameMalayalam": "ലൂക്കോസ്",
  "bookNameEnglish": "Luke",
  "writerMalayalam": "ലൂക്കോസ്",
  "writerEnglish": "Luke",
  "dateInEnglish": "A.D. 58-63 (assumption)",
  "dateInMalayalam": "ഏ.ഡി. 58-63 (അനുമാനം)",
  "categoryInEnglish": "Gospel",
  "categoryInMalayalam": "സുവിശേഷം"
}