{
  "verse": "അവർ അവനെ കൊളുത്തിട്ടു ഒരു കൂട്ടിൽ ആക്കി ബാബേൽരാജാവിന്റെ അടുക്കൽ കൊണ്ടുപോയി; ഇനി അവന്റെ നാദം യിസ്രായേൽപർവ്വതങ്ങളിൽ കേൾക്കാതെയിരിക്കേണ്ടതിന്നു അവർ അവനെ ദുർഗ്ഗങ്ങളിൽ കൊണ്ടുപോയി.",
  "book": "26",
  "chapterCount": "48",
  "chapter": "19",
  "verseCountInBook": "1273",
  "verseCountInChapter": "14",
  "verseNumber": "9",
  "bookNameMalayalam": "യെഹെസ്കേൽ",
  "bookNameEnglish": "Ezekiel",
  "writerMalayalam": "യെഹെസ്കേൽ",
  "writerEnglish": "Ezekiel",
  "dateInEnglish": "B.C. 571 (assumption)",
  "dateInMalayalam": "ബി.സി. 571 (അനുമാനം)",
  "categoryInEnglish": "Prophecy",
  "categoryInMalayalam": "പ്രവചനം"
}