{
  "verse": "യഹോവയായ ഞാൻ ഉയരമുള്ള വൃക്ഷത്തെ താഴ്ത്തി താണിരുന്ന വൃക്ഷത്തെ ഉയർത്തുകയും പച്ചയായുള്ള വൃക്ഷത്തെ ഉണക്കി ഉണങ്ങിയ വൃക്ഷത്തെ തഴെപ്പിക്കയും ചെയ്തിരിക്കുന്നു എന്നു കാട്ടിലെ സകലവൃക്ഷങ്ങളും അറിയും; യഹോവയായ ഞാൻ അതു പ്രസ്താവിച്ചും അനുഷ്ഠിച്ചും ഇരിക്കുന്നു.",
  "book": "26",
  "chapterCount": "48",
  "chapter": "17",
  "verseCountInBook": "1273",
  "verseCountInChapter": "24",
  "verseNumber": "24",
  "bookNameMalayalam": "യെഹെസ്കേൽ",
  "bookNameEnglish": "Ezekiel",
  "writerMalayalam": "യെഹെസ്കേൽ",
  "writerEnglish": "Ezekiel",
  "dateInEnglish": "B.C. 571 (assumption)",
  "dateInMalayalam": "ബി.സി. 571 (അനുമാനം)",
  "categoryInEnglish": "Prophecy",
  "categoryInMalayalam": "പ്രവചനം"
}