{
  "verse": "എന്നാൽ നിങ്ങളെ ഏല്പിക്കുമ്പോൾ എങ്ങനെയോ എന്തോ പറയേണ്ടു എന്നു വിചാരപ്പെടേണ്ടാ; പറവാനുള്ളതു ആ നാഴികയിൽ തന്നേ നിങ്ങൾക്കു ലഭിക്കും.",
  "book": "40",
  "chapterCount": "28",
  "chapter": "10",
  "verseCountInBook": "1071",
  "verseCountInChapter": "42",
  "verseNumber": "19",
  "bookNameMalayalam": "മത്തായി",
  "bookNameEnglish": "Matthew",
  "writerMalayalam": "മത്തായി",
  "writerEnglish": "Matthew",
  "dateInEnglish": "A.D. 37 (assumption)",
  "dateInMalayalam": "ഏ.ഡി. 37",
  "categoryInEnglish": "Gospel",
  "categoryInMalayalam": "സുവിശേഷം"
}