{
  "verse": "നിങ്ങൾ യുദ്ധങ്ങളെയും യുദ്ധശ്രുതികളെയും കുറിച്ചുകേൾക്കും; ചഞ്ചലപ്പെടാതിരിപ്പാൻ സൂക്ഷിച്ചുകൊൾവിൻ; അതു സംഭവിക്കേണ്ടതു തന്നേ;",
  "book": "40",
  "chapterCount": "28",
  "chapter": "24",
  "verseCountInBook": "1071",
  "verseCountInChapter": "51",
  "verseNumber": "6",
  "bookNameMalayalam": "മത്തായി",
  "bookNameEnglish": "Matthew",
  "writerMalayalam": "മത്തായി",
  "writerEnglish": "Matthew",
  "dateInEnglish": "A.D. 37 (assumption)",
  "dateInMalayalam": "ഏ.ഡി. 37",
  "categoryInEnglish": "Gospel",
  "categoryInMalayalam": "സുവിശേഷം"
}