{
  "verse": "അതിന്റെ ശേഷം അബ്രാഹാം തന്റെ ഭാര്യയായ സാറയെ കനാൻ ദേശത്തിലെ ഹെബ്രോൻ എന്ന മമ്രേക്കരികെയുള്ള മക്ക്പേലാനിലത്തിലെ ഗുഹയിൽ അടക്കം ചെയ്തു.",
  "book": "1",
  "chapterCount": "50",
  "chapter": "23",
  "verseCountInBook": "1533",
  "verseCountInChapter": "20",
  "verseNumber": "19",
  "bookNameMalayalam": "ഉല്‍‍പത്തി",
  "bookNameEnglish": "Genesis",
  "writerMalayalam": "മോശെ",
  "writerEnglish": "Moses",
  "dateInEnglish": "B.C. 1450-1410 (assumption)",
  "dateInMalayalam": "ബി.സി. 1450-1410 (അനുമാനം)",
  "categoryInEnglish": "Law",
  "categoryInMalayalam": "നിയമം"
}