{
  "verse": "നെബൂഖദ് നേസർരാജാവു പൊന്നുകൊണ്ടു ഒരു ബിംബം ഉണ്ടാക്കി; അതിന്റെ ഉയരം അറുപതു മുഴവും വണ്ണം ആറു മുഴവും ആയിരുന്നു; അവൻ അതിനെ ബാബേൽസംസ്ഥാനത്തു ദുരാസമഭൂമിയിൽ നിർത്തി.",
  "book": "27",
  "chapterCount": "12",
  "chapter": "3",
  "verseCountInBook": "357",
  "verseCountInChapter": "30",
  "verseNumber": "1",
  "bookNameMalayalam": "ദാനീയേല്‍",
  "bookNameEnglish": "Daniel",
  "writerMalayalam": "ദാനീയേല്‍",
  "writerEnglish": "Daniel",
  "dateInEnglish": "B.C. 535 (assumption)",
  "dateInMalayalam": "ബി.സി. 535 (അനുമാനം)",
  "categoryInEnglish": "Prophecy",
  "categoryInMalayalam": "പ്രവചനം"
}