{
  "verse": "യിസ്രായേലേ, ഗിബെയയുടെ കാലംമുതൽ നീ പാപം ചെയ്തിരിക്കുന്നു; അവർ അവിടെത്തന്നേ നിൽക്കുന്നു; ഗിബെയയിൽ നീതികെട്ടവരോടുള്ള പട അവരെ എത്തിപ്പിടിച്ചില്ല;",
  "book": "28",
  "chapterCount": "14",
  "chapter": "10",
  "verseCountInBook": "197",
  "verseCountInChapter": "15",
  "verseNumber": "9",
  "bookNameMalayalam": "ഹോശേയ",
  "bookNameEnglish": "Hosea",
  "writerMalayalam": "ഹോശേയ",
  "writerEnglish": "Hosea",
  "dateInEnglish": "B.C. 715 (assumption)",
  "dateInMalayalam": "ബി.സി. 715 (അനുമാനം)",
  "categoryInEnglish": "Prophecy",
  "categoryInMalayalam": "പ്രവചനം"
}