{
  "verse": "മൂന്നാമതും അവൻ അമ്പതുപേർക്കു അധിപതിയായ ഒരുത്തനെയും അവന്റെ അമ്പതു ആളെയും അയച്ചു; ഈ മൂന്നാമത്തെ അമ്പതുപേർക്കു അധിപതിയായവൻ ചെന്നു ഏലീയാവിന്റെ മുമ്പിൽ മുട്ടുകുത്തി അവനോടു: ദൈവപുരുഷനായുള്ളോവേ, എന്റെ പ്രാണനെയും നിന്റെ ദാസന്മാരായ ഈ അമ്പതു ആളുടെ പ്രാണനെയും ആദരിക്കേണമേ.",
  "book": "12",
  "chapterCount": "25",
  "chapter": "1",
  "verseCountInBook": "719",
  "verseCountInChapter": "18",
  "verseNumber": "13",
  "bookNameMalayalam": "2 രാജാക്കന്മാർ",
  "bookNameEnglish": "2 Kings",
  "writerMalayalam": "യിരെമ്യാവ്‌",
  "writerEnglish": "Jeremiah",
  "dateInEnglish": "B.C. 580 (assumption)",
  "dateInMalayalam": "ബി.സി. 580 (അനുമാനം)",
  "categoryInEnglish": "History",
  "categoryInMalayalam": "ചരിത്രം"
}