{
  "verse": "മിസ്രയീംദേശത്തിന്റെ മരുഭൂമിയിൽവെച്ചു നിങ്ങളുടെ പിതാക്കന്മാരോടു ഞാൻ വ്യവഹരിച്ചതുപോലെ നിങ്ങളോടും വ്യവഹരിക്കും എന്നു യഹോവയായ കർത്താവിന്റെ അരുളപ്പാടു.",
  "book": "26",
  "chapterCount": "48",
  "chapter": "20",
  "verseCountInBook": "1273",
  "verseCountInChapter": "49",
  "verseNumber": "36",
  "bookNameMalayalam": "യെഹെസ്കേൽ",
  "bookNameEnglish": "Ezekiel",
  "writerMalayalam": "യെഹെസ്കേൽ",
  "writerEnglish": "Ezekiel",
  "dateInEnglish": "B.C. 571 (assumption)",
  "dateInMalayalam": "ബി.സി. 571 (അനുമാനം)",
  "categoryInEnglish": "Prophecy",
  "categoryInMalayalam": "പ്രവചനം"
}