{
  "verse": "അപ്പോൾ ചുറ്റും നിൽക്കുന്നവരുടെ മുമ്പിൽ തന്നെത്താൻ അടക്കുവാൻ വഹിയാതെ: എല്ലാവരെയും എന്റെ അടുക്കൽ നിന്നു പുറത്താക്കുവിൻ എന്നു യോസേഫ് വിളിച്ചുപറഞ്ഞു. ഇങ്ങനെ യോസേഫ് തന്റെ സഹോദരന്മാർക്കു തന്നെ വെളിപ്പെടുത്തിയപ്പോൾ ആരും അടുക്കൽ ഉണ്ടായിരുന്നില്ല.",
  "book": "1",
  "chapterCount": "50",
  "chapter": "45",
  "verseCountInBook": "1533",
  "verseCountInChapter": "28",
  "verseNumber": "1",
  "bookNameMalayalam": "ഉല്‍‍പത്തി",
  "bookNameEnglish": "Genesis",
  "writerMalayalam": "മോശെ",
  "writerEnglish": "Moses",
  "dateInEnglish": "B.C. 1450-1410 (assumption)",
  "dateInMalayalam": "ബി.സി. 1450-1410 (അനുമാനം)",
  "categoryInEnglish": "Law",
  "categoryInMalayalam": "നിയമം"
}