{
  "verse": "എന്റെ കോപം അവരുടെ നേരെ ജ്വലിച്ചിട്ടു ഞാൻ അവരെ ഉപേക്ഷിക്കയും എന്റെ മുഖം അവർക്കു മറെക്കയും ചെയ്യും; അവർ നാശത്തിന്നിരയായ്തീരും; അനേകം അനർത്ഥങ്ങളും കഷ്ടങ്ങളും അവർക്കു ഭവിക്കും; നമ്മുടെ ദൈവം നമ്മുടെ ഇടയിൽ ഇല്ലായ്കകൊണ്ടല്ലയോ ഈ അനത്ഥങ്ങൾ നമുക്കു ഭവിച്ചതു എന്നു അവർ അന്നു പറയും.",
  "book": "5",
  "chapterCount": "34",
  "chapter": "31",
  "verseCountInBook": "959",
  "verseCountInChapter": "30",
  "verseNumber": "17",
  "bookNameMalayalam": "ആവർത്തനപുസ്തകം",
  "bookNameEnglish": "Deuteronomy",
  "writerMalayalam": "മോശെ",
  "writerEnglish": "Moses",
  "dateInEnglish": "B.C. 1407-1406 (assumption)",
  "dateInMalayalam": "ബി.സി. 1407-1406 (അനുമാനം)",
  "categoryInEnglish": "Law",
  "categoryInMalayalam": "നിയമം"
}