{
  "verse": "ഞങ്ങൾക്കു മുമ്പായി നടപ്പാൻ ദൈവങ്ങളെ ഉണ്ടാക്കിത്തരിക; ഞങ്ങളെ മിസ്രയീമിൽനിന്നു നടത്തിക്കൊണ്ടുവന്ന ആ മോശെക്കു എന്തു സംഭവിച്ചു എന്നു ഞങ്ങൾ അറിയുന്നില്ലല്ലോ എന്നു പറഞ്ഞു.",
  "book": "44",
  "chapterCount": "28",
  "chapter": "7",
  "verseCountInBook": "1007",
  "verseCountInChapter": "60",
  "verseNumber": "40",
  "bookNameMalayalam": "അപ്പൊസ്തലന്മാരുടെ പ്രവൃത്തികൾ",
  "bookNameEnglish": "Acts of the Apostles",
  "writerMalayalam": "വൈദ്യനായ ലൂക്കോസ്",
  "writerEnglish": "Luke the physician",
  "dateInEnglish": "A.D. 63",
  "dateInMalayalam": "ഏ.ഡി. 63",
  "categoryInEnglish": "History",
  "categoryInMalayalam": "ചരിത്രം"
}