{
  "verse": "അവന്റെ തലയിൽ വെടിപ്പുള്ളോരു മുടി വെക്കട്ടെ എന്നു അവൻ കല്പിച്ചു; അങ്ങനെ അവർ അവന്റെ തലയിൽ വെടിപ്പുള്ളോരു മുടി വെച്ചു. അവനെ വസ്ത്രം ധരിപ്പിച്ചു യഹോവയുടെ ദൂതനോ അടുക്കെ നിൽക്കയായിരുന്നു.",
  "book": "38",
  "chapterCount": "14",
  "chapter": "3",
  "verseCountInBook": "211",
  "verseCountInChapter": "10",
  "verseNumber": "5",
  "bookNameMalayalam": "സെഖര്യാവ്",
  "bookNameEnglish": "Zechariah",
  "writerMalayalam": "സെഖര്യാവ്",
  "writerEnglish": "Zechariah",
  "dateInEnglish": "B.C.520-518 , chapters 1-8 ; B.C. 480 , chapters 9-14",
  "dateInMalayalam": "ബി.സി. 520-518, 1-8 അദ്ധ്യായങ്ങൾ; ബി.സി. 480, 9-14 അദ്ധ്യായങ്ങൾ",
  "categoryInEnglish": "Prophecy",
  "categoryInMalayalam": "പ്രവചനം"
}