{
  "verse": "അവർ അവന്നു ഒരു കഷണം അത്തിയടയും രണ്ടു ഉണക്കമുന്തിരിക്കുലയും കൊടുത്തു; അതു തിന്നപ്പോൾ അവന്നു ഉയിർവീണു; മൂന്നു രാവും മൂന്നു പകലും അവൻ ആഹാരം കഴിക്കയോ വെള്ളം കുടിക്കയോ ചെയ്തിട്ടില്ലായിരുന്നു.",
  "book": "9",
  "chapterCount": "31",
  "chapter": "30",
  "verseCountInBook": "810",
  "verseCountInChapter": "31",
  "verseNumber": "12",
  "bookNameMalayalam": "1 ശമൂവേൽ",
  "bookNameEnglish": "1 Samuel",
  "writerMalayalam": "ശമുവേൽ (നാഥാൻ, ഗാദ്)",
  "writerEnglish": "Samuel (Nathan, Gad)",
  "dateInEnglish": "Not clear",
  "dateInMalayalam": "വ്യക്തമല്ല",
  "categoryInEnglish": "History",
  "categoryInMalayalam": "ചരിത്രം"
}