{
  "verse": "കർത്താവു അരാമ്യസൈന്യത്തെ രഥങ്ങളുടെയും കുതിരകളുടെയും മഹാസൈന്യത്തിന്റെയും ആരവം കേൾപ്പിച്ചിരുന്നതുകൊണ്ടു അവർ തമ്മിൽ തമ്മിൽ: ഇതാ, നമ്മുടെ നേരെ വരേണ്ടതിന്നു യിസ്രായേൽരാജാവു ഹിത്യരാജാക്കന്മാരെയും മിസ്രയീംരാജാക്കന്മാരെയും നമുക്കു വിരോധമായി കൂലിക്കു വാങ്ങിയിരിക്കുന്നു എന്നു പറഞ്ഞു.",
  "book": "12",
  "chapterCount": "25",
  "chapter": "7",
  "verseCountInBook": "719",
  "verseCountInChapter": "20",
  "verseNumber": "6",
  "bookNameMalayalam": "2 രാജാക്കന്മാർ",
  "bookNameEnglish": "2 Kings",
  "writerMalayalam": "യിരെമ്യാവ്‌",
  "writerEnglish": "Jeremiah",
  "dateInEnglish": "B.C. 580 (assumption)",
  "dateInMalayalam": "ബി.സി. 580 (അനുമാനം)",
  "categoryInEnglish": "History",
  "categoryInMalayalam": "ചരിത്രം"
}