{
  "verse": "അവർക്കു മതിയാകുംവണ്ണം ആടുകളെയും മാടുകളെയും അവർക്കുവേണ്ടി അറുക്കുമോ? അവർക്കു മതിയാകുംവണ്ണം സമുദ്രത്തിലെ മത്സ്യത്തെ ഒക്കെയും അവർക്കു വേണ്ടി പിടിച്ചുകൂട്ടുമോ എന്നു ചോദിച്ചു.",
  "book": "4",
  "chapterCount": "36",
  "chapter": "11",
  "verseCountInBook": "1288",
  "verseCountInChapter": "35",
  "verseNumber": "22",
  "bookNameMalayalam": "സംഖ്യാപുസ്തകം",
  "bookNameEnglish": "Numbers",
  "writerMalayalam": "മോശെ",
  "writerEnglish": "Moses",
  "dateInEnglish": "B.C. 1445-1405 (assumption)",
  "dateInMalayalam": "ബി.സി. 1445-1405 (അനുമാനം)",
  "categoryInEnglish": "Law",
  "categoryInMalayalam": "നിയമം"
}