{
  "verse": "എന്റെ വായിൽ നിന്നു പുറപ്പെടുന്ന എന്റെ വചനം ആയിരിക്കും; അതു വെറുതെ എന്റെ അടുക്കലേക്കു മടങ്ങിവരാതെ എനിക്കു ഇഷ്ടമുള്ളതു നിവർ‍ത്തിക്കയും ഞാൻ അയച്ച കാര്യം സാധിപ്പിക്കയും ചെയ്യും.",
  "book": "23",
  "chapterCount": "66",
  "chapter": "55",
  "verseCountInBook": "1292",
  "verseCountInChapter": "13",
  "verseNumber": "11",
  "bookNameMalayalam": "യെശയ്യാവ്",
  "bookNameEnglish": "Isaiah",
  "writerMalayalam": "യെശയ്യാവ്",
  "writerEnglish": "Isaiah",
  "dateInEnglish": "B.C. 740-680",
  "dateInMalayalam": "ബി.സി. 740-680",
  "categoryInEnglish": "Prophecy",
  "categoryInMalayalam": "പ്രവചനം"
}