{
  "verse": "അപ്പോൾ തന്നേ കൈസര്യയിൽ നിന്നു എന്റെ അടുക്കൽ അയച്ചിരുന്ന മൂന്നു പുരുഷന്മാർ ഞങ്ങൾ പാർത്ത വീട്ടിന്റെ മുമ്പിൽ നിന്നിരുന്നു;",
  "book": "44",
  "chapterCount": "28",
  "chapter": "11",
  "verseCountInBook": "1007",
  "verseCountInChapter": "30",
  "verseNumber": "11",
  "bookNameMalayalam": "അപ്പൊസ്തലന്മാരുടെ പ്രവൃത്തികൾ",
  "bookNameEnglish": "Acts of the Apostles",
  "writerMalayalam": "വൈദ്യനായ ലൂക്കോസ്",
  "writerEnglish": "Luke the physician",
  "dateInEnglish": "A.D. 63",
  "dateInMalayalam": "ഏ.ഡി. 63",
  "categoryInEnglish": "History",
  "categoryInMalayalam": "ചരിത്രം"
}