{
  "verse": "ഇപ്പോൾ കർത്താവിന്റെ കൈ നിന്റെ മേൽ വീഴും; നീ ഒരു സമയത്തേക്കു സൂര്യനെ കാണാതെ കുരുടനായിരിക്കും എന്നു പറഞ്ഞു. ഉടനെ ഒരു തിമിരവും ഇരുട്ടും അവന്റെ മേൽ വീണു; കൈപിടിച്ചു നടത്തുന്നവരെ തിരഞ്ഞുകൊണ്ടു അവൻ തപ്പിനടന്നു.",
  "book": "44",
  "chapterCount": "28",
  "chapter": "13",
  "verseCountInBook": "1007",
  "verseCountInChapter": "52",
  "verseNumber": "11",
  "bookNameMalayalam": "അപ്പൊസ്തലന്മാരുടെ പ്രവൃത്തികൾ",
  "bookNameEnglish": "Acts of the Apostles",
  "writerMalayalam": "വൈദ്യനായ ലൂക്കോസ്",
  "writerEnglish": "Luke the physician",
  "dateInEnglish": "A.D. 63",
  "dateInMalayalam": "ഏ.ഡി. 63",
  "categoryInEnglish": "History",
  "categoryInMalayalam": "ചരിത്രം"
}