{
  "verse": "യെഹൂദന്മാരോ പുരുഷാരത്തെ കണ്ടു അസൂയ നിറഞ്ഞവരായി ദുഷിച്ചുകൊണ്ടു പൌലൊസ് സംസാരിക്കുന്നതിന്നു എതിർ പറഞ്ഞു.",
  "book": "44",
  "chapterCount": "28",
  "chapter": "13",
  "verseCountInBook": "1007",
  "verseCountInChapter": "52",
  "verseNumber": "45",
  "bookNameMalayalam": "അപ്പൊസ്തലന്മാരുടെ പ്രവൃത്തികൾ",
  "bookNameEnglish": "Acts of the Apostles",
  "writerMalayalam": "വൈദ്യനായ ലൂക്കോസ്",
  "writerEnglish": "Luke the physician",
  "dateInEnglish": "A.D. 63",
  "dateInMalayalam": "ഏ.ഡി. 63",
  "categoryInEnglish": "History",
  "categoryInMalayalam": "ചരിത്രം"
}