{
  "verse": "നീ മൽക്കീസേദെക്കിന്റെ ക്രമപ്രകാരം എന്നേക്കും പുരോഹിതൻ എന്നല്ലോ സാക്ഷീകരിച്ചിരിക്കുന്നതു.",
  "book": "58",
  "chapterCount": "13",
  "chapter": "7",
  "verseCountInBook": "303",
  "verseCountInChapter": "28",
  "verseNumber": "17",
  "bookNameMalayalam": "എബ്രായർ",
  "bookNameEnglish": "Hebrews",
  "writerMalayalam": "പൌലൊസ് (അനുമാനം)",
  "writerEnglish": "Paul (assumption)",
  "dateInEnglish": "A.D. 64",
  "dateInMalayalam": "ഏ.ഡി. 64",
  "categoryInEnglish": "Epistle",
  "categoryInMalayalam": "ലേഖനം"
}