{
  "verse": "മുമ്പിലത്തെ കല്പനെക്കു അതിന്റെ ബലഹീനതയും നിഷ്‌പ്രയോജനവുംനിമിത്തം",
  "book": "58",
  "chapterCount": "13",
  "chapter": "7",
  "verseCountInBook": "303",
  "verseCountInChapter": "28",
  "verseNumber": "18",
  "bookNameMalayalam": "എബ്രായർ",
  "bookNameEnglish": "Hebrews",
  "writerMalayalam": "പൌലൊസ് (അനുമാനം)",
  "writerEnglish": "Paul (assumption)",
  "dateInEnglish": "A.D. 64",
  "dateInMalayalam": "ഏ.ഡി. 64",
  "categoryInEnglish": "Epistle",
  "categoryInMalayalam": "ലേഖനം"
}