{
  "verse": "നമ്മുടെ കർത്താവായ യേശുക്രിസ്തുമുഖാന്തരം നമ്മുടെ രക്ഷിതാവായ ഏകദൈവത്തിന്നു തന്നേ, സർവ്വകാലത്തിന്നുമുമ്പും ഇപ്പോഴും സദാകാലത്തോളവും തേജസ്സും മഹിമയും ബലവും അധികാരവും ഉണ്ടാകുമാറാകട്ടെ. ആമേൻ.",
  "book": "65",
  "chapterCount": "1",
  "chapter": "1",
  "verseCountInBook": "25",
  "verseCountInChapter": "25",
  "verseNumber": "25",
  "bookNameMalayalam": "യൂദാ",
  "bookNameEnglish": "Jude",
  "writerMalayalam": "യേശുവിന്റെയും യാക്കോബിന്റെയും സഹോദരനായ യൂദാ",
  "writerEnglish": "Judas, the brother of Jesus and James",
  "dateInEnglish": "A.D. 65",
  "dateInMalayalam": "ഏ.ഡി. 65",
  "categoryInEnglish": "Epistle",
  "categoryInMalayalam": "ലേഖനം"
}