{
  "verse": "അതിനെ അശുദ്ധമാക്കുന്നവൻ മരണശിക്ഷ അനുഭവിക്കേണം. ആരെങ്കിലും അന്നു വേല ചെയ്താൽ അവനെ അവന്റെ ജനത്തിന്റെ ഇടയിൽനിന്നു ഛേദിച്ചുകളയേണം.",
  "book": "2",
  "chapterCount": "40",
  "chapter": "31",
  "verseCountInBook": "1213",
  "verseCountInChapter": "18",
  "verseNumber": "14",
  "bookNameMalayalam": "പുറപ്പാട്",
  "bookNameEnglish": "Exodus",
  "writerMalayalam": "മോശെ",
  "writerEnglish": "Moses",
  "dateInEnglish": "B.C. 1450-1405 (assumption)",
  "dateInMalayalam": "ബി.സി. 1450-1405 (അനുമാനം)",
  "categoryInEnglish": "Law",
  "categoryInMalayalam": "നിയമം"
}