{
  "verse": "ഞാൻ യെരൂശലേമിൽ നമസ്കരിപ്പാൻ പോയിട്ടു പന്ത്രണ്ടു നാളിൽ അധികമായില്ല എന്നു നിനക്കു അറിയാകുന്നതാകുന്നു.",
  "book": "44",
  "chapterCount": "28",
  "chapter": "24",
  "verseCountInBook": "1007",
  "verseCountInChapter": "27",
  "verseNumber": "11",
  "bookNameMalayalam": "അപ്പൊസ്തലന്മാരുടെ പ്രവൃത്തികൾ",
  "bookNameEnglish": "Acts of the Apostles",
  "writerMalayalam": "വൈദ്യനായ ലൂക്കോസ്",
  "writerEnglish": "Luke the physician",
  "dateInEnglish": "A.D. 63",
  "dateInMalayalam": "ഏ.ഡി. 63",
  "categoryInEnglish": "History",
  "categoryInMalayalam": "ചരിത്രം"
}