{
  "verse": "വ്യാജവും ഭോഷ്കും എന്നോടു അകറ്റേണമേ; ദാരിദ്ര്യവും സമ്പത്തും എനിക്കു തരാതെ നിത്യവൃത്തി തന്നു എന്നെ പോഷിപ്പിക്കേണമേ.",
  "book": "20",
  "chapterCount": "31",
  "chapter": "30",
  "verseCountInBook": "915",
  "verseCountInChapter": "33",
  "verseNumber": "8",
  "bookNameMalayalam": "സദൃശവാക്യങ്ങൾ",
  "bookNameEnglish": "Proverbs",
  "writerMalayalam": "ശലോമോൻ, ആഗൂർ, ലെമൂവേൽ",
  "writerEnglish": "Solomon, Agur, Lemuel",
  "dateInEnglish": "B.C. 1000 (assumption). In 730 B.C., Hezekiah collected and assembled 25-29 Chapters.",
  "dateInMalayalam": "ബി.സി. 1000 (അനുമാനം) 25-29 അദ്ധ്യായങ്ങൾ ബി.സി. 730-ൽ ഹിസ്കീയാവ് ശേഖരിച്ചു കൂട്ടിച്ചേർത്തു.",
  "categoryInEnglish": "Poetry",
  "categoryInMalayalam": "കാവ്യം"
}