{
  "verse": "പണിയുന്നവർ യഹോവയുടെ മന്ദിരത്തിന്നു അടിസ്ഥാനം ഇട്ടപ്പോൾ യിസ്രായേൽരാജാവായ ദാവീദിന്റെ ചട്ടപ്രകാരം യഹോവെക്കു സ്തോത്രം ചെയ്യേണ്ടതിന്നു വിശുദ്ധവസ്ത്രം ധരിച്ച പുരോഹിതന്മാരെ കാഹളങ്ങളോടും ആസാഫ്യരായ ലേവ്യരെ കൈത്താളങ്ങളോടുംകൂടെ നിർത്തി.",
  "book": "15",
  "chapter": "3",
  "verseNumber": "10",
  "bookNameMalayalam": "എസ്രാ",
  "bookNameEnglish": "Ezra",
  "writerMalayalam": "എസ്രാ",
  "writerEnglish": "Ezra",
  "dateInEnglish": "B.C. 450 (assumption)",
  "dateInMalayalam": "ബി.സി. 450 (അനുമാനം)",
  "categoryInEnglish": "History",
  "categoryInMalayalam": "ചരിത്രം",
  "bookSummary": "യെരൂശലേമിലേക്കും, യെഹൂദായിലേക്കുമുള്ള യെഹൂദന്മാരുടെ മടങ്ങിവരവ്, ദൈവാലയത്തിന്റെ പുനർനിർമ്മാണം; യെഹൂദന്മാർ നേരിട്ട എതിർപ്പുകൾ; അവരുടെ വിജയം; സെരുബ്ബാബേലിന്റെയും, എസ്രായുടേയും നേതൃത്വം."
}