{
  "verse": "നീ ചിറകു വിടർത്തു മറെക്കുന്ന കെരൂബ് ആകുന്നു; ഞാൻ നിന്നെ വിശുദ്ധദേവപർവ്വതത്തിൽ ഇരുത്തിയിരുന്നു; നീ അഗ്നിമയരഥങ്ങളുടെ മദ്ധ്യേ സഞ്ചരിച്ചുപോന്നു.",
  "book": "26",
  "chapterCount": "48",
  "chapter": "28",
  "verseCountInBook": "1273",
  "verseCountInChapter": "26",
  "verseNumber": "14",
  "bookNameMalayalam": "യെഹെസ്കേൽ",
  "bookNameEnglish": "Ezekiel",
  "writerMalayalam": "യെഹെസ്കേൽ",
  "writerEnglish": "Ezekiel",
  "dateInEnglish": "B.C. 571 (assumption)",
  "dateInMalayalam": "ബി.സി. 571 (അനുമാനം)",
  "categoryInEnglish": "Prophecy",
  "categoryInMalayalam": "പ്രവചനം"
}