{
  "verse": "അഥേനയിൽ പൌലൊസ് അവർക്കായി കാത്തിരിക്കുമ്പോൾ നഗരത്തിൽ ബിംബങ്ങൾ നിറഞ്ഞിരിക്കുന്നതു കണ്ടു മനസ്സിന്നു ചൂടുപിടിച്ചു.",
  "book": "44",
  "chapterCount": "28",
  "chapter": "17",
  "verseCountInBook": "1007",
  "verseCountInChapter": "34",
  "verseNumber": "16",
  "bookNameMalayalam": "അപ്പൊസ്തലന്മാരുടെ പ്രവൃത്തികൾ",
  "bookNameEnglish": "Acts of the Apostles",
  "writerMalayalam": "വൈദ്യനായ ലൂക്കോസ്",
  "writerEnglish": "Luke the physician",
  "dateInEnglish": "A.D. 63",
  "dateInMalayalam": "ഏ.ഡി. 63",
  "categoryInEnglish": "History",
  "categoryInMalayalam": "ചരിത്രം"
}