{
  "verse": "വിഗ്രഹങ്ങളെ ഉണ്ടാക്കരുതു; ബിംബമോ സ്തംഭമോ നാട്ടരുതു; രൂപം കൊത്തിയ യാതൊരു കല്ലും നമസ്കരിപ്പാൻ നിങ്ങളുടെ ദേശത്തു നാട്ടുകയും അരുതു; ഞാൻ നിങ്ങളുടെ ദൈവമായ യഹോവ ആകുന്നു.",
  "book": "3",
  "chapterCount": "27",
  "chapter": "26",
  "verseCountInBook": "859",
  "verseCountInChapter": "46",
  "verseNumber": "1",
  "bookNameMalayalam": "ലേവ്യപുസ്തകം",
  "bookNameEnglish": "Leviticus",
  "writerMalayalam": "മോശെ",
  "writerEnglish": "Moses",
  "dateInEnglish": "B.C. 1445-1405 (assumption)",
  "dateInMalayalam": "ബി.സി. 1445-1405 (അനുമാനം)",
  "categoryInEnglish": "Law",
  "categoryInMalayalam": "നിയമം"
}