{
  "verse": "വിശ്വാസത്താൽ മോശെയുടെ ജനനത്തിങ്കൽ ശിശു സുന്ദരൻ എന്നു അമ്മയപ്പന്മാർ കണ്ടു: രാജാവിന്റെ കല്പന ഭയപ്പെടാതെ അവനെ മൂന്നു മാസം ഒളിപ്പിച്ചുവെച്ചു.",
  "book": "58",
  "chapterCount": "13",
  "chapter": "11",
  "verseCountInBook": "303",
  "verseCountInChapter": "40",
  "verseNumber": "23",
  "bookNameMalayalam": "എബ്രായർ",
  "bookNameEnglish": "Hebrews",
  "writerMalayalam": "പൌലൊസ് (അനുമാനം)",
  "writerEnglish": "Paul (assumption)",
  "dateInEnglish": "A.D. 64",
  "dateInMalayalam": "ഏ.ഡി. 64",
  "categoryInEnglish": "Epistle",
  "categoryInMalayalam": "ലേഖനം"
}