{
  "verse": "അവൻ വന്നു പാപത്തെക്കുറിച്ചും നീതിയെക്കുറിച്ചും ന്യായവിധിയെക്കുറിച്ചും ലോകത്തിന്നു ബോധം വരുത്തും.",
  "book": "43",
  "chapterCount": "21",
  "chapter": "16",
  "verseCountInBook": "879",
  "verseCountInChapter": "33",
  "verseNumber": "8",
  "bookNameMalayalam": "യോഹന്നാന്‍",
  "bookNameEnglish": "John",
  "writerMalayalam": "യോഹന്നാന്‍",
  "writerEnglish": "John",
  "dateInEnglish": "A.D. 90 (assumption)",
  "dateInMalayalam": "ഏ.ഡി. 90 (അനുമാനം)",
  "categoryInEnglish": "Gospel",
  "categoryInMalayalam": "സുവിശേഷം"
}