{
  "verse": "അവന്നു മുപ്പതു കഴുതപ്പുറത്തു കയറി ഓടിക്കുന്ന മുപ്പതു പുത്രന്മാർ ഉണ്ടായിരുന്നു; അവർക്കു മുപ്പതു ഊരുകളും ഉണ്ടായിരുന്നു; അവെക്കു ഇന്നുവരെയും ഹവ്വോത്ത്-യായീർ എന്നു പേർ പറയുന്നു; അവ ഗിലെയാദ് ദേശത്തു ആകുന്നു.",
  "book": "7",
  "chapterCount": "21",
  "chapter": "10",
  "verseCountInBook": "618",
  "verseCountInChapter": "18",
  "verseNumber": "4",
  "bookNameMalayalam": "ന്യായാധിപന്മാർ",
  "bookNameEnglish": "Judges",
  "writerMalayalam": "ശമുവേൽ",
  "writerEnglish": "Samuel",
  "dateInEnglish": "B.C. 1050 (assumption)",
  "dateInMalayalam": "ബി.സി. 1050 (അനുമാനം)",
  "categoryInEnglish": "History",
  "categoryInMalayalam": "ചരിത്രം"
}