{
  "verse": "കഷ്ടത്തിൽ ആയപ്പോൾ അവൻ തന്റെ ദൈവമായ യഹോവയോടു അപേക്ഷിച്ചു. തന്റെ പിതാക്കന്മാരുടെ ദൈവത്തിന്റെ മുമ്പിൽ തന്നെത്താൻ ഏറ്റവും താഴ്ത്തി അവനോടു പ്രാർത്ഥിച്ചു.",
  "book": "14",
  "chapterCount": "36",
  "chapter": "33",
  "verseCountInBook": "822",
  "verseCountInChapter": "25",
  "verseNumber": "12",
  "bookNameMalayalam": "2 ദിനവൃത്താന്തം",
  "bookNameEnglish": "2 Chronicles",
  "writerMalayalam": "എസ്രാ (യെഹൂദാ പാരമ്പര്യം)",
  "writerEnglish": "Ezra (Jewish tradition)",
  "dateInEnglish": "B.C. 458-430",
  "dateInMalayalam": "ബി.സി. 458-430",
  "categoryInEnglish": "History",
  "categoryInMalayalam": "ചരിത്രം"
}