{
  "verse": "വെള്ളികൊണ്ടു രണ്ടു കാഹളം ഉണ്ടാക്കുക; അടിപ്പു പണിയായി അവയെ ഉണ്ടാക്കേണം; അവ നിനക്കു സഭയെ വിളിച്ചുകൂട്ടുവാനും പാളയത്തെ പുറപ്പെടുവിപ്പാനും ഉതകേണം.",
  "book": "4",
  "chapterCount": "36",
  "chapter": "10",
  "verseCountInBook": "1288",
  "verseCountInChapter": "36",
  "verseNumber": "2",
  "bookNameMalayalam": "സംഖ്യാപുസ്തകം",
  "bookNameEnglish": "Numbers",
  "writerMalayalam": "മോശെ",
  "writerEnglish": "Moses",
  "dateInEnglish": "B.C. 1445-1405 (assumption)",
  "dateInMalayalam": "ബി.സി. 1445-1405 (അനുമാനം)",
  "categoryInEnglish": "Law",
  "categoryInMalayalam": "നിയമം"
}